gsa_geothermal/__init__.py
gsa_geothermal-0.1.dev1.dist-info/LICENSE
gsa_geothermal-0.1.dev1.dist-info/METADATA
gsa_geothermal-0.1.dev1.dist-info/WHEEL
gsa_geothermal-0.1.dev1.dist-info/top_level.txt
gsa_geothermal-0.1.dev1.dist-info/RECORD
