Metadata-Version: 2.1
Name: gsa-geothermal
Version: 0.1.dev1
Summary: Global sensitivity analysis for conventional and enhanced geothermal power plants
Home-page: https://github.com/a-pau/gsa_geothermal
Author: Andrea Paulillo
Author-email: andrea.paulillo@ucl.ac.uk
License: UNKNOWN
Platform: UNKNOWN
Classifier: Programming Language :: Python :: 3
Classifier: License :: OSI Approved :: BSD License
Classifier: Operating System :: OS Independent
Requires-Python: >=3.6
